mpti/__init__.py
mpti/dir_import_man.py
mpti-0.0.2.dist-info/LICENSE
mpti-0.0.2.dist-info/METADATA
mpti-0.0.2.dist-info/WHEEL
mpti-0.0.2.dist-info/top_level.txt
mpti-0.0.2.dist-info/RECORD
